<?xml version="1.0" encoding="utf-8"?>
<!DOCTYPE hibernate-mapping PUBLIC "-//Hibernate/Hibernate Mapping DTD 3.0//EN"
"http://hibernate.sourceforge.net/hibernate-mapping-3.0.dtd">
<!-- 
    Mapping file autogenerated by MyEclipse Persistence Tools
-->
<hibernate-mapping>
    <class name="sedion.jeffli.wmuitp.entity.CourseChapter" table="course_chapter" catalog="itp">
        <id name="ccId" type="java.lang.Integer">
            <column name="CC_Id" />
            <generator class="identity" />
        </id>
        <many-to-one name="course" class="sedion.jeffli.wmuitp.entity.Course" fetch="select">
            <column name="C_Id" />
        </many-to-one>
        <property name="ccName" type="java.lang.String">
            <column name="CC_Name" length="20" />
        </property>
        <property name="ccSign" type="java.lang.String">
            <column name="CC_Sign" length="20" />
        </property>
        <set name="subjectInfors" inverse="true">
            <key>
                <column name="CC_Id" />
            </key>
            <one-to-many class="sedion.jeffli.wmuitp.entity.SubjectInfor" />
        </set>
    </class>
</hibernate-mapping>
